fcswrite/__init__.py
fcswrite/_version.py
fcswrite/fcswrite.py
fcswrite-0.6.4.dist-info/licenses/LICENSE
fcswrite-0.6.4.dist-info/METADATA
fcswrite-0.6.4.dist-info/WHEEL
fcswrite-0.6.4.dist-info/top_level.txt
fcswrite-0.6.4.dist-info/RECORD
