Metadata-Version: 2.4
Name: fcswrite
Version: 0.6.4
Summary: Write .fcs files (flow cytometry)
Author: Paul Müller, Philipp Rosendahl
Maintainer-email: Paul Müller <dev@craban.de>
License: BSD-3-Clause
Project-URL: source, https://github.com/DC-analysis/fcswrite
Project-URL: tracker, https://github.com/DC-analysis/fcswrite/issues
Project-URL: changelog, https://raw.githubusercontent.com/DC-analysis/fcswrite/refs/heads/master/CHANGELOG
Keywords: fcs,flow cytometry,flow cytometry standard
Classifier: Operating System :: OS Independent
Classifier: Programming Language :: Python :: 3
Classifier: Topic :: Scientific/Engineering :: Visualization
Classifier: Intended Audience :: Science/Research
Requires-Python: <4,>=3.6
License-File: LICENSE
Requires-Dist: numpy>=1.22.0
Dynamic: license-file
